medizintechnik_oct/OCT_GUI.py
medizintechnik_oct/__init__.py
medizintechnik_oct/__main__.py
medizintechnik_oct/src/__init__.py
medizintechnik_oct/src/AzureTTK/.git
medizintechnik_oct/src/AzureTTK/.gitignore
medizintechnik_oct/src/AzureTTK/Dark screenshot.png
medizintechnik_oct/src/AzureTTK/LICENSE
medizintechnik_oct/src/AzureTTK/Light screenshot.png
medizintechnik_oct/src/AzureTTK/README.md
medizintechnik_oct/src/AzureTTK/azure.tcl
medizintechnik_oct/src/AzureTTK/example.py
medizintechnik_oct/src/AzureTTK/screenshot.png
medizintechnik_oct/src/AzureTTK/theme/dark.tcl
medizintechnik_oct/src/AzureTTK/theme/light.tcl
medizintechnik_oct/src/AzureTTK/theme/dark/box-accent.png
medizintechnik_oct/src/AzureTTK/theme/dark/box-basic.png
medizintechnik_oct/src/AzureTTK/theme/dark/box-hover.png
medizintechnik_oct/src/AzureTTK/theme/dark/box-invalid.png
medizintechnik_oct/src/AzureTTK/theme/dark/button-hover.png
medizintechnik_oct/src/AzureTTK/theme/dark/card.png
medizintechnik_oct/src/AzureTTK/theme/dark/check-accent.png
medizintechnik_oct/src/AzureTTK/theme/dark/check-basic.png
medizintechnik_oct/src/AzureTTK/theme/dark/check-hover.png
medizintechnik_oct/src/AzureTTK/theme/dark/check-tri-accent.png
medizintechnik_oct/src/AzureTTK/theme/dark/check-tri-basic.png
medizintechnik_oct/src/AzureTTK/theme/dark/check-tri-hover.png
medizintechnik_oct/src/AzureTTK/theme/dark/circle-accent.png
medizintechnik_oct/src/AzureTTK/theme/dark/circle-basic.png
medizintechnik_oct/src/AzureTTK/theme/dark/circle-hover.png
medizintechnik_oct/src/AzureTTK/theme/dark/combo-button-basic.png
medizintechnik_oct/src/AzureTTK/theme/dark/combo-button-focus.png
medizintechnik_oct/src/AzureTTK/theme/dark/combo-button-hover.png
medizintechnik_oct/src/AzureTTK/theme/dark/down-accent.png
medizintechnik_oct/src/AzureTTK/theme/dark/down.png
medizintechnik_oct/src/AzureTTK/theme/dark/empty.png
medizintechnik_oct/src/AzureTTK/theme/dark/hor-accent.png
medizintechnik_oct/src/AzureTTK/theme/dark/hor-basic.png
medizintechnik_oct-1.1.dist-info/LICENSE
medizintechnik_oct-1.1.dist-info/METADATA
medizintechnik_oct-1.1.dist-info/WHEEL
medizintechnik_oct-1.1.dist-info/entry_points.txt
medizintechnik_oct-1.1.dist-info/top_level.txt
medizintechnik_oct-1.1.dist-info/RECORD
